kclvm_py-0.4.4.1.data/data/checksum.txt
kclvm_py-0.4.4.1.data/data/gpyrpc.proto
kclvm_py-0.4.4.1.data/data/kcl.lark
kclvm_py-0.4.4.1.data/data/kcl.proto
kclvm_py-0.4.4.1.data/data/md.mako
kclvm_py-0.4.4.1.data/data/model.proto
kclvm_py-0.4.4.1.data/data/modfile.proto
kclvm_py-0.4.4.1.data/data/protorpc_wire.proto
kclvm_py-0.4.4.1.data/data/requirements.txt
kclvm_py-0.4.4.1.data/purelib/kclvm/__init__.py
kclvm_py-0.4.4.1.data/purelib/kclvm/__main__.py
kclvm_py-0.4.4.1.data/purelib/kclvm/api/__init__.py
kclvm_py-0.4.4.1.data/purelib/kclvm/api/object/__init__.py
kclvm_py-0.4.4.1.data/purelib/kclvm/api/object/bytecode.py
kclvm_py-0.4.4.1.data/purelib/kclvm/api/object/decorator.py
kclvm_py-0.4.4.1.data/purelib/kclvm/api/object/function.py
kclvm_py-0.4.4.1.data/purelib/kclvm/api/object/object.py
kclvm_py-0.4.4.1.data/purelib/kclvm/api/object/schema.py
kclvm_py-0.4.4.1.data/purelib/kclvm/api/object/internal/__init__.py
kclvm_py-0.4.4.1.data/purelib/kclvm/api/object/internal/common.py
kclvm_py-0.4.4.1.data/purelib/kclvm/api/object/internal/decorators.py
kclvm_py-0.4.4.1.data/purelib/kclvm/api/object/internal/option.py
kclvm_py-0.4.4.1.data/purelib/kclvm/api/object/internal/path_selector.py
kclvm_py-0.4.4.1.data/purelib/kclvm/api/object/internal/selector.py
kclvm_py-0.4.4.1.data/purelib/kclvm/api/object/internal/undefined.py
kclvm_py-0.4.4.1.data/purelib/kclvm/api/version/__init__.py
kclvm_py-0.4.4.1.data/purelib/kclvm/api/version/__main__.py
kclvm_py-0.4.4.1.data/purelib/kclvm/api/version/checksum.txt
kclvm_py-0.4.4.1.data/purelib/kclvm/api/version/version.py
kclvm_py-0.4.4.1.data/purelib/kclvm/compiler/__init__.py
kclvm_py-0.4.4.1.data/purelib/kclvm/compiler/astutil/__init__.py
kclvm_py-0.4.4.1.data/purelib/kclvm/compiler/astutil/builder.py
kclvm_py-0.4.4.1.data/purelib/kclvm/compiler/astutil/filter.py
kclvm_py-0.4.4.1.data/purelib/kclvm/compiler/astutil/fix.py
kclvm_py-0.4.4.1.data/purelib/kclvm/compiler/build/__init__.py
kclvm_py-0.4.4.1.dist-info/LICENSE
kclvm_py-0.4.4.1.dist-info/METADATA
kclvm_py-0.4.4.1.dist-info/WHEEL
kclvm_py-0.4.4.1.dist-info/top_level.txt
kclvm_py-0.4.4.1.dist-info/zip-safe
kclvm_py-0.4.4.1.dist-info/RECORD
